pud/__init__.py
pud/__main__.py
pud/app.py
pud/entity.py
pud/main.py
pud/options.py
pud/utils.py
pud/handlers/__init__.py
pud/handlers/directory.py
pud-1.1.0.dist-info/LICENSE
pud-1.1.0.dist-info/METADATA
pud-1.1.0.dist-info/WHEEL
pud-1.1.0.dist-info/entry_points.txt
pud-1.1.0.dist-info/top_level.txt
pud-1.1.0.dist-info/RECORD
