Metadata-Version: 2.1
Name: pud
Version: 1.1.0
Summary: A command-line tool for navigating directories.
Home-page: https://github.com/Jedddy/pud
Author: Jedddy
License: UNKNOWN
Platform: UNKNOWN
Classifier: Programming Language :: Python :: 3
Classifier: License :: OSI Approved :: MIT License
Classifier: Operating System :: OS Independent
Requires-Python: >=3.9
License-File: LICENSE
Requires-Dist: windows-curses (==2.3.1) ; sys_platform == "win32"
